[{"winner":{"name":"김유미","score":3,"level":"1"},"loser":{"name":"김용남","score":0,"level":"5"}},{"winner":{"name":"김유미","score":3,"level":"1"},"loser":{"name":"문경옥","score":0,"level":"6"}},{"winner":{"name":"김유미","score":3,"level":"1"},"loser":{"name":"권혁순","score":0,"level":"6"}},{"winner":{"name":"김유미","score":3,"level":"1"},"loser":{"name":"박성동","score":0,"level":"6"}},{"winner":{"name":"김유미","score":3,"level":"1"},"loser":{"name":"정미균","score":1,"level":"6"}},{"winner":{"name":"김용남","score":3,"level":"5"},"loser":{"name":"문경옥","score":1,"level":"6"}},{"winner":{"name":"김용남","score":3,"level":"5"},"loser":{"name":"권혁순","score":1,"level":"6"}},{"winner":{"name":"김용남","score":3,"level":"5"},"loser":{"name":"박성동","score":0,"level":"6"}},{"winner":{"name":"김용남","score":3,"level":"5"},"loser":{"name":"정미균","score":0,"level":"6"}},{"winner":{"name":"문경옥","score":3,"level":"6"},"loser":{"name":"권혁순","score":0,"level":"6"}},{"winner":{"name":"문경옥","score":3,"level":"6"},"loser":{"name":"박성동","score":2,"level":"6"}},{"winner":{"name":"문경옥","score":3,"level":"6"},"loser":{"name":"정미균","score":1,"level":"6"}},{"winner":{"name":"박성동","score":3,"level":"6"},"loser":{"name":"권혁순","score":0,"level":"6"}},{"winner":{"name":"정미균","score":3,"level":"6"},"loser":{"name":"권혁순","score":0,"level":"6"}},{"winner":{"name":"정미균","score":3,"level":"6"},"loser":{"name":"박성동","score":0,"level":"6"}},{"winner":{"name":"최보은","score":3,"level":"3"},"loser":{"name":"홍수민","score":0,"level":"6"}},{"winner":{"name":"최보은","score":3,"level":"3"},"loser":{"name":"김창진","score":0,"level":"6"}},{"winner":{"name":"최보은","score":3,"level":"3"},"loser":{"name":"서영보","score":0,"level":"6"}},{"winner":{"name":"최보은","score":3,"level":"3"},"loser":{"name":"김영만","score":0,"level":"6"}},{"winner":{"name":"김창진","score":3,"level":"6"},"loser":{"name":"홍수민","score":1,"level":"6"}},{"winner":{"name":"서영보","score":3,"level":"6"},"loser":{"name":"홍수민","score":2,"level":"6"}},{"winner":{"name":"홍수민","score":3,"level":"6"},"loser":{"name":"김영만","score":0,"level":"6"}},{"winner":{"name":"김창진","score":3,"level":"6"},"loser":{"name":"서영보","score":1,"level":"6"}},{"winner":{"name":"김영만","score":3,"level":"6"},"loser":{"name":"김창진","score":2,"level":"6"}},{"winner":{"name":"김영만","score":3,"level":"6"},"loser":{"name":"서영보","score":1,"level":"6"}},{"winner":{"name":"강향순","score":3,"level":"4"},"loser":{"name":"박청호","score":1,"level":"5"}},{"winner":{"name":"강향순","score":3,"level":"4"},"loser":{"name":"현성환","score":0,"level":"6"}},{"winner":{"name":"이영숙","score":3,"level":"6"},"loser":{"name":"강향순","score":0,"level":"4"}},{"winner":{"name":"강향순","score":3,"level":"4"},"loser":{"name":"이호준","score":0,"level":"6"}},{"winner":{"name":"강향순","score":3,"level":"4"},"loser":{"name":"정종환","score":0,"level":"6"}},{"winner":{"name":"박청호","score":3,"level":"5"},"loser":{"name":"현성환","score":2,"level":"6"}},{"winner":{"name":"이영숙","score":3,"level":"6"},"loser":{"name":"박청호","score":1,"level":"5"}},{"winner":{"name":"박청호","score":3,"level":"5"},"loser":{"name":"이호준","score":1,"level":"6"}},{"winner":{"name":"박청호","score":3,"level":"5"},"loser":{"name":"정종환","score":1,"level":"6"}},{"winner":{"name":"이영숙","score":3,"level":"6"},"loser":{"name":"현성환","score":0,"level":"6"}},{"winner":{"name":"현성환","score":3,"level":"6"},"loser":{"name":"이호준","score":1,"level":"6"}},{"winner":{"name":"정종환","score":3,"level":"6"},"loser":{"name":"현성환","score":1,"level":"6"}},{"winner":{"name":"이영숙","score":3,"level":"6"},"loser":{"name":"이호준","score":2,"level":"6"}},{"winner":{"name":"이영숙","score":3,"level":"6"},"loser":{"name":"정종환","score":1,"level":"6"}},{"winner":{"name":"정종환","score":3,"level":"6"},"loser":{"name":"이호준","score":1,"level":"6"}},{"winner":{"name":"박웅","score":3,"level":"5"},"loser":{"name":"여현동","score":0,"level":"6"}},{"winner":{"name":"길한철","score":3,"level":"6"},"loser":{"name":"박웅","score":2,"level":"5"}},{"winner":{"name":"박웅","score":3,"level":"5"},"loser":{"name":"공윤수","score":0,"level":"6"}},{"winner":{"name":"박웅","score":3,"level":"5"},"loser":{"name":"조경호","score":0,"level":"7"}},{"winner":{"name":"최재민","score":3,"level":"6"},"loser":{"name":"박웅","score":1,"level":"5"}},{"winner":{"name":"길한철","score":3,"level":"6"},"loser":{"name":"여현동","score":0,"level":"6"}},{"winner":{"name":"공윤수","score":3,"level":"6"},"loser":{"name":"여현동","score":1,"level":"6"}},{"winner":{"name":"여현동","score":3,"level":"6"},"loser":{"name":"조경호","score":0,"level":"7"}},{"winner":{"name":"최재민","score":3,"level":"6"},"loser":{"name":"여현동","score":2,"level":"6"}},{"winner":{"name":"길한철","score":3,"level":"6"},"loser":{"name":"공윤수","score":0,"level":"6"}},{"winner":{"name":"길한철","score":3,"level":"6"},"loser":{"name":"조경호","score":1,"level":"7"}},{"winner":{"name":"최재민","score":3,"level":"6"},"loser":{"name":"길한철","score":1,"level":"6"}},{"winner":{"name":"조경호","score":3,"level":"7"},"loser":{"name":"공윤수","score":2,"level":"6"}},{"winner":{"name":"최재민","score":3,"level":"6"},"loser":{"name":"공윤수","score":0,"level":"6"}},{"winner":{"name":"최재민","score":3,"level":"6"},"loser":{"name":"조경호","score":0,"level":"7"}},{"winner":{"name":"심민수","score":3,"level":"5"},"loser":{"name":"여현동","score":0,"level":"6"}},{"winner":{"name":"최승헌","score":3,"level":"6"},"loser":{"name":"심민수","score":1,"level":"5"}},{"winner":{"name":"박진호","score":3,"level":"6"},"loser":{"name":"심민수","score":1,"level":"5"}},{"winner":{"name":"심민수","score":3,"level":"5"},"loser":{"name":"윤영균","score":0,"level":"6"}},{"winner":{"name":"심민수","score":3,"level":"5"},"loser":{"name":"성흡창","score":0,"level":"7"}},{"winner":{"name":"최승헌","score":3,"level":"6"},"loser":{"name":"여현동","score":0,"level":"6"}},{"winner":{"name":"박진호","score":3,"level":"6"},"loser":{"name":"여현동","score":1,"level":"6"}},{"winner":{"name":"윤영균","score":3,"level":"6"},"loser":{"name":"여현동","score":0,"level":"6"}},{"winner":{"name":"여현동","score":3,"level":"6"},"loser":{"name":"성흡창","score":1,"level":"7"}},{"winner":{"name":"박진호","score":3,"level":"6"},"loser":{"name":"최승헌","score":2,"level":"6"}},{"winner":{"name":"윤영균","score":3,"level":"6"},"loser":{"name":"최승헌","score":1,"level":"6"}},{"winner":{"name":"최승헌","score":3,"level":"6"},"loser":{"name":"성흡창","score":0,"level":"7"}},{"winner":{"name":"윤영균","score":3,"level":"6"},"loser":{"name":"박진호","score":2,"level":"6"}},{"winner":{"name":"박진호","score":3,"level":"6"},"loser":{"name":"성흡창","score":2,"level":"7"}},{"winner":{"name":"윤영균","score":3,"level":"6"},"loser":{"name":"성흡창","score":2,"level":"7"}},{"winner":{"name":"이동명","score":3,"level":"5"},"loser":{"name":"유승희","score":0,"level":"6"}},{"winner":{"name":"이동명","score":3,"level":"5"},"loser":{"name":"박옥희","score":0,"level":"6"}},{"winner":{"name":"이동명","score":3,"level":"5"},"loser":{"name":"이상협","score":0,"level":"6"}},{"winner":{"name":"이동명","score":3,"level":"5"},"loser":{"name":"정정호","score":1,"level":"6"}},{"winner":{"name":"이동명","score":3,"level":"5"},"loser":{"name":"김경석","score":0,"level":"7"}},{"winner":{"name":"박옥희","score":3,"level":"6"},"loser":{"name":"유승희","score":0,"level":"6"}},{"winner":{"name":"유승희","score":3,"level":"6"},"loser":{"name":"이상협","score":2,"level":"6"}},{"winner":{"name":"정정호","score":3,"level":"6"},"loser":{"name":"유승희","score":0,"level":"6"}},{"winner":{"name":"유승희","score":3,"level":"6"},"loser":{"name":"김경석","score":1,"level":"7"}},{"winner":{"name":"이상협","score":3,"level":"6"},"loser":{"name":"박옥희","score":0,"level":"6"}},{"winner":{"name":"정정호","score":3,"level":"6"},"loser":{"name":"박옥희","score":0,"level":"6"}},{"winner":{"name":"박옥희","score":3,"level":"6"},"loser":{"name":"김경석","score":0,"level":"7"}},{"winner":{"name":"정정호","score":3,"level":"6"},"loser":{"name":"이상협","score":0,"level":"6"}},{"winner":{"name":"이상협","score":3,"level":"6"},"loser":{"name":"김경석","score":0,"level":"7"}},{"winner":{"name":"정정호","score":3,"level":"6"},"loser":{"name":"김경석","score":0,"level":"7"}},{"winner":{"name":"김기철","score":3,"level":"5"},"loser":{"name":"전중한","score":1,"level":"6"}},{"winner":{"name":"임숙희","score":3,"level":"6"},"loser":{"name":"김기철","score":2,"level":"5"}},{"winner":{"name":"김기철","score":3,"level":"5"},"loser":{"name":"서원하","score":0,"level":"6"}},{"winner":{"name":"김기철","score":3,"level":"5"},"loser":{"name":"천권장","score":0,"level":"6"}},{"winner":{"name":"김기철","score":3,"level":"5"},"loser":{"name":"조은숙","score":1,"level":"6"}},{"winner":{"name":"임숙희","score":3,"level":"6"},"loser":{"name":"전중한","score":0,"level":"6"}},{"winner":{"name":"전중한","score":3,"level":"6"},"loser":{"name":"서원하","score":1,"level":"6"}},{"winner":{"name":"전중한","score":3,"level":"6"},"loser":{"name":"천권장","score":0,"level":"6"}},{"winner":{"name":"조은숙","score":3,"level":"6"},"loser":{"name":"전중한","score":2,"level":"6"}},{"winner":{"name":"임숙희","score":3,"level":"6"},"loser":{"name":"서원하","score":1,"level":"6"}},{"winner":{"name":"임숙희","score":3,"level":"6"},"loser":{"name":"천권장","score":0,"level":"6"}},{"winner":{"name":"임숙희","score":3,"level":"6"},"loser":{"name":"조은숙","score":2,"level":"6"}},{"winner":{"name":"서원하","score":3,"level":"6"},"loser":{"name":"천권장","score":2,"level":"6"}},{"winner":{"name":"조은숙","score":3,"level":"6"},"loser":{"name":"서원하","score":0,"level":"6"}},{"winner":{"name":"조은숙","score":3,"level":"6"},"loser":{"name":"천권장","score":0,"level":"6"}}]