[{"winner":{"name":"김기철","score":3,"level":"5"},"loser":{"name":"이상근","score":2,"level":"3"}},{"winner":{"name":"김익수","score":3,"level":"6"},"loser":{"name":"이상근","score":2,"level":"3"}},{"winner":{"name":"이상근","score":3,"level":"3"},"loser":{"name":"이관욱","score":2,"level":"6"}},{"winner":{"name":"이상근","score":3,"level":"3"},"loser":{"name":"김창진","score":2,"level":"6"}},{"winner":{"name":"조성제","score":3,"level":"5"},"loser":{"name":"이상근","score":0,"level":"3"}},{"winner":{"name":"김익수","score":3,"level":"6"},"loser":{"name":"김기철","score":1,"level":"5"}},{"winner":{"name":"이관욱","score":3,"level":"6"},"loser":{"name":"김기철","score":2,"level":"5"}},{"winner":{"name":"김기철","score":3,"level":"5"},"loser":{"name":"김창진","score":0,"level":"6"}},{"winner":{"name":"조성제","score":3,"level":"5"},"loser":{"name":"김기철","score":2,"level":"5"}},{"winner":{"name":"김익수","score":3,"level":"6"},"loser":{"name":"이관욱","score":2,"level":"6"}},{"winner":{"name":"김창진","score":3,"level":"6"},"loser":{"name":"김익수","score":1,"level":"6"}},{"winner":{"name":"김익수","score":3,"level":"6"},"loser":{"name":"조성제","score":0,"level":"5"}},{"winner":{"name":"김창진","score":3,"level":"6"},"loser":{"name":"이관욱","score":0,"level":"6"}},{"winner":{"name":"조성제","score":3,"level":"5"},"loser":{"name":"이관욱","score":1,"level":"6"}},{"winner":{"name":"김창진","score":3,"level":"6"},"loser":{"name":"조성제","score":1,"level":"5"}},{"winner":{"name":"장희진","score":3,"level":"4"},"loser":{"name":"조용식","score":2,"level":"5"}},{"winner":{"name":"이원형","score":3,"level":"5"},"loser":{"name":"장희진","score":1,"level":"4"}},{"winner":{"name":"장희진","score":3,"level":"4"},"loser":{"name":"송성산","score":2,"level":"6"}},{"winner":{"name":"정은경","score":3,"level":"6"},"loser":{"name":"장희진","score":2,"level":"4"}},{"winner":{"name":"정다은","score":3,"level":"6"},"loser":{"name":"장희진","score":2,"level":"4"}},{"winner":{"name":"조용식","score":3,"level":"5"},"loser":{"name":"이원형","score":1,"level":"5"}},{"winner":{"name":"조용식","score":3,"level":"5"},"loser":{"name":"송성산","score":1,"level":"6"}},{"winner":{"name":"조용식","score":3,"level":"5"},"loser":{"name":"정은경","score":1,"level":"6"}},{"winner":{"name":"조용식","score":3,"level":"5"},"loser":{"name":"정다은","score":1,"level":"6"}},{"winner":{"name":"송성산","score":3,"level":"6"},"loser":{"name":"이원형","score":2,"level":"5"}},{"winner":{"name":"정은경","score":3,"level":"6"},"loser":{"name":"이원형","score":0,"level":"5"}},{"winner":{"name":"이원형","score":3,"level":"5"},"loser":{"name":"정다은","score":0,"level":"6"}},{"winner":{"name":"송성산","score":3,"level":"6"},"loser":{"name":"정은경","score":0,"level":"6"}},{"winner":{"name":"송성산","score":3,"level":"6"},"loser":{"name":"정다은","score":1,"level":"6"}},{"winner":{"name":"정다은","score":3,"level":"6"},"loser":{"name":"정은경","score":0,"level":"6"}},{"winner":{"name":"홍영희","score":3,"level":"4"},"loser":{"name":"김치승","score":0,"level":"5"}},{"winner":{"name":"이승찬","score":3,"level":"6"},"loser":{"name":"홍영희","score":2,"level":"4"}},{"winner":{"name":"홍영희","score":3,"level":"4"},"loser":{"name":"홍두선","score":1,"level":"6"}},{"winner":{"name":"홍영희","score":3,"level":"4"},"loser":{"name":"김광래","score":2,"level":"6"}},{"winner":{"name":"홍영희","score":3,"level":"4"},"loser":{"name":"김주호","score":0,"level":"6"}},{"winner":{"name":"이승찬","score":3,"level":"6"},"loser":{"name":"김치승","score":1,"level":"5"}},{"winner":{"name":"홍두선","score":3,"level":"6"},"loser":{"name":"김치승","score":0,"level":"5"}},{"winner":{"name":"김광래","score":3,"level":"6"},"loser":{"name":"김치승","score":1,"level":"5"}},{"winner":{"name":"김치승","score":3,"level":"5"},"loser":{"name":"김주호","score":1,"level":"6"}},{"winner":{"name":"이승찬","score":3,"level":"6"},"loser":{"name":"홍두선","score":1,"level":"6"}},{"winner":{"name":"김광래","score":3,"level":"6"},"loser":{"name":"이승찬","score":2,"level":"6"}},{"winner":{"name":"이승찬","score":3,"level":"6"},"loser":{"name":"김주호","score":0,"level":"6"}},{"winner":{"name":"홍두선","score":3,"level":"6"},"loser":{"name":"김광래","score":0,"level":"6"}},{"winner":{"name":"홍두선","score":3,"level":"6"},"loser":{"name":"김주호","score":0,"level":"6"}},{"winner":{"name":"김광래","score":3,"level":"6"},"loser":{"name":"김주호","score":0,"level":"6"}},{"winner":{"name":"김은주","score":3,"level":"4"},"loser":{"name":"정기원","score":1,"level":"6"}},{"winner":{"name":"김은주","score":3,"level":"4"},"loser":{"name":"장대석","score":0,"level":"6"}},{"winner":{"name":"김은주","score":3,"level":"4"},"loser":{"name":"김동순","score":0,"level":"6"}},{"winner":{"name":"조은숙","score":3,"level":"6"},"loser":{"name":"김은주","score":2,"level":"4"}},{"winner":{"name":"김은주","score":3,"level":"4"},"loser":{"name":"이광훈","score":2,"level":"5"}},{"winner":{"name":"정기원","score":3,"level":"6"},"loser":{"name":"장대석","score":1,"level":"6"}},{"winner":{"name":"정기원","score":3,"level":"6"},"loser":{"name":"김동순","score":1,"level":"6"}},{"winner":{"name":"조은숙","score":3,"level":"6"},"loser":{"name":"정기원","score":0,"level":"6"}},{"winner":{"name":"이광훈","score":3,"level":"5"},"loser":{"name":"정기원","score":0,"level":"6"}},{"winner":{"name":"김동순","score":3,"level":"6"},"loser":{"name":"장대석","score":0,"level":"6"}},{"winner":{"name":"장대석","score":3,"level":"6"},"loser":{"name":"조은숙","score":2,"level":"6"}},{"winner":{"name":"이광훈","score":3,"level":"5"},"loser":{"name":"장대석","score":2,"level":"6"}},{"winner":{"name":"조은숙","score":3,"level":"6"},"loser":{"name":"김동순","score":1,"level":"6"}},{"winner":{"name":"이광훈","score":3,"level":"5"},"loser":{"name":"김동순","score":0,"level":"6"}},{"winner":{"name":"이광훈","score":3,"level":"5"},"loser":{"name":"조은숙","score":2,"level":"6"}},{"winner":{"name":"송호진","score":3,"level":"5"},"loser":{"name":"이영숙","score":2,"level":"6"}},{"winner":{"name":"송호진","score":3,"level":"5"},"loser":{"name":"김영만","score":2,"level":"6"}},{"winner":{"name":"송호진","score":3,"level":"5"},"loser":{"name":"유혁종","score":0,"level":"6"}},{"winner":{"name":"송호진","score":3,"level":"5"},"loser":{"name":"유승아","score":0,"level":"6"}},{"winner":{"name":"송호진","score":3,"level":"5"},"loser":{"name":"정정호","score":1,"level":"5"}},{"winner":{"name":"김영만","score":3,"level":"6"},"loser":{"name":"이영숙","score":0,"level":"6"}},{"winner":{"name":"이영숙","score":3,"level":"6"},"loser":{"name":"유혁종","score":0,"level":"6"}},{"winner":{"name":"이영숙","score":3,"level":"6"},"loser":{"name":"유승아","score":0,"level":"6"}},{"winner":{"name":"정정호","score":3,"level":"5"},"loser":{"name":"이영숙","score":0,"level":"6"}},{"winner":{"name":"김영만","score":3,"level":"6"},"loser":{"name":"유혁종","score":0,"level":"6"}},{"winner":{"name":"김영만","score":3,"level":"6"},"loser":{"name":"유승아","score":2,"level":"6"}},{"winner":{"name":"정정호","score":3,"level":"5"},"loser":{"name":"김영만","score":2,"level":"6"}},{"winner":{"name":"유승아","score":3,"level":"6"},"loser":{"name":"유혁종","score":0,"level":"6"}},{"winner":{"name":"정정호","score":3,"level":"5"},"loser":{"name":"유혁종","score":0,"level":"6"}},{"winner":{"name":"정정호","score":3,"level":"5"},"loser":{"name":"유승아","score":0,"level":"6"}}]